pywxdump/WX_OFFS.json
pywxdump/__init__.py
pywxdump/wx_core/__init__.py
pywxdump/wx_core/decryption.py
pywxdump/wx_core/get_bias_addr.py
pywxdump/wx_core/memory_search.py
pywxdump/wx_core/merge_db.py
pywxdump/wx_core/wx_info.py
pywxdump/wx_core/utils/__init__.py
pywxdump/wx_core/utils/_loger.py
pywxdump/wx_core/utils/common_utils.py
pywxdump/wx_core/utils/ctypes_utils.py
pywxdump/wx_core/utils/memory_search.py
dpwx-0.1.5.dist-info/METADATA
dpwx-0.1.5.dist-info/WHEEL
dpwx-0.1.5.dist-info/top_level.txt
dpwx-0.1.5.dist-info/RECORD
