Metadata-Version: 2.1
Name: dpwx
Version: 0.1.5
Summary: my package
Requires-Dist: pymem
